exalt/__init__.py
exalt/__main__.py
exalt/source.py
exalt_for_humans-0.1.0.dist-info/METADATA
exalt_for_humans-0.1.0.dist-info/WHEEL
exalt_for_humans-0.1.0.dist-info/entry_points.txt
exalt_for_humans-0.1.0.dist-info/RECORD
