Metadata-Version: 2.1
Name: exalt-for-humans
Version: 0.1.0
Summary: Create beautiful code images with exalt!
Home-page: https://github.com/JnyJny/exalt.git
Author: JnyJny
Author-email: erik.oshaughnessy@gmail.com
Requires-Python: >=3.12,<4.0
Classifier: Programming Language :: Python :: 3
Classifier: Programming Language :: Python :: 3.12
Requires-Dist: loguru (>=0.7.2,<0.8.0)
Requires-Dist: pyvips (>=2.2.2,<3.0.0)
Requires-Dist: rich (>=13.7.0,<14.0.0)
Requires-Dist: typer (>=0.9.0,<0.10.0)
Project-URL: Repository, https://github.com/JnyJny/exalt.git
